fast_orient/__init__.py
fast_orient/client.py
fast_orient/logger.py
fast_orient/main.py
fast_orient-0.0.0.dist-info/METADATA
fast_orient-0.0.0.dist-info/WHEEL
fast_orient-0.0.0.dist-info/top_level.txt
fast_orient-0.0.0.dist-info/RECORD
